[
  {
    "date": "20/03/2026",
    "titles": [
      "Détection de minéraux réox sensibles dans les roches martiennes par Perseverance",
      "Éclairs martiens détectés par la NASA transformant la chimie organique",
      "Cinquième nucléobase ADN découverte dans échantillons de Bennu",
      "Le 'Jerk' sismique pour prédire les éruptions volcaniques en avance",
      "Mission chinoise de sauvetage après collision en orbite"
    ]
  },
  {
    "date": "21/03/2026",
    "titles": []
  },
  {
    "date": "22/03/2026",
    "titles": [
      "Supernovas superlumineuses alimentées par des magnétars : oscillations de luminosité détectées",
      "Doolysaurus : nouveau dinosaure juvénile découvert en Corée du Sud",
      "Neutrino ultra-énergétique détecté : possiblement originaire d'un blazar",
      "Découverte d'une protéine responsable de l'addiction à la cocaïne",
      "Sensibilité des hérissons aux ultrasons : implications pour leur protection",
      "Toutes les bases de l'ADN détectées sur l'astéroïde Bennu"
    ]
  },
  {
    "date": "22/03/2026",
    "titles": [
      "Oscillations de luminosité dans la supernova superlumineuse 2024afav confirmées par quatre sursauts",
      "Détection de silice cristallisée (opale, calcédoine, quartz) dans le cratère Jezero par Perseverance",
      "Première identification de minéraux réox sensibles sur Mars par Perseverance",
      "Observation de microcharges électrostatiques dues à des grains minéraux sur Mars",
      "Corrélation potentiellement importante découverte pour la matière noire"
    ]
  },
  {
    "date": "22/03/2026",
    "titles": [
      "Oscillations de luminosité confirmées dans la supernova superlumineuse 2024afav par quatre sursauts",
      "Corrélation potentiellement importante découverte pour la matière noire",
      "Protéine responsable de l'addiction à la cocaïne identifiée",
      "Neutrino ultra-énergétique détecté, possiblement issu d'un blazar",
      "Hérissons sensibles aux ultrasons, implications pour leur protection"
    ]
  },
  {
    "date": "22/03/2026",
    "titles": [
      "Détection de silice cristallisée dans le cratère Jezero par Perseverance",
      "Première identification de minéraux réox sensibles sur Mars",
      "Observation de microcharges électrostatiques sur Mars",
      "Suzetrigine : premier médicament sélectif contre la douleur périphérique",
      "Édition CRISPR des racines pour cultures résistantes à la sécheresse"
    ]
  },
  {
    "date": "22/03/2026",
    "titles": [
      "Origine de la vie : ressuscitation d'une enzyme vieille de 3 milliards d'années",
      "Éclairs trahissant la présence de trous noirs binaires",
      "Cellule visuelle unique découverte chez les poissons des abysses",
      "Détection du neutrino le plus énergétique, possiblement d'un blazar",
      "Protéine responsable de l'addiction à la cocaïne identifiée"
    ]
  }
]